{"data": {"user": {"result": {"__typename": "User", "timeline_v2": {"timeline": {"instructions": [{"type": "TimelinePinEntry", "entry": {"entryId": "tweet-1790068965126852770", "sortIndex": "1779110906735623271", "content": {"entryType": "TimelineTimelineItem", "__typename": "TimelineTimelineItem", "itemContent": {"itemType": "TimelineTweet", "__typename": "TimelineTweet", "tweet_results": {"result": {"__typename": "Tweet", "rest_id": "1790068965126852770", "core": {"user_results": {"result": {"__typename": "User", "id": "VXNlcjoxMTE0MjUzMDI=", "rest_id": "111425302", "affiliates_highlighted_label": {}, "has_graduated_access": true, "is_blue_verified": true, "profile_image_shape": "Circle", "legacy": {"can_dm": false, "can_media_tag": true, "created_at": "Thu Feb 04 21:57:18 +0000 2010", "default_profile": false, "default_profile_image": false, "description": "OXXXYMIRON \u2014 \u041c\u0418\u0420 \u0413\u041e\u0420\u0418\u0422 (2024): https://t.co/vWDJNHj6yc", "entities": {"description": {"urls": [{"display_url": "band.link/mirgorit", "expanded_url": "https://band.link/mirgorit", "url": "https://t.co/vWDJNHj6yc", "indices": [31, 54]}]}}, "fast_followers_count": 0, "favourites_count": 8088, "followers_count": 1321795, "friends_count": 1, "has_custom_timelines": false, "is_translator": false, "listed_count": 1011, "location": "", "media_count": 2298, "name": "Oxxxymiron", "normal_followers_count": 1321795, "pinned_tweet_ids_str": ["1790068965126852770"], "possibly_sensitive": false, "profile_banner_url": "https://pbs.twimg.com/profile_banners/111425302/1704298013", "profile_image_url_https": "https://pbs.twimg.com/profile_images/1745576847717380096/5VaX9j39_normal.jpg", "profile_interstitial_type": "", "screen_name": "norimyxxxo", "statuses_count": 14877, "translator_type": "none", "verified": false, "want_retweets": false, "withheld_in_countries": []}, "tipjar_settings": {}}}}, "unmention_data": {}, "edit_control": {"edit_tweet_ids": ["1790068965126852770"], "editable_until_msecs": "1715624273000", "is_edit_eligible": true, "edits_remaining": "5"}, "is_translatable": false, "views": {"count": "151142", "state": "EnabledWithCount"}, "source": "<a href=\"http://twitter.com/download/iphone\" rel=\"nofollow\">Twitter for iPhone</a>", "legacy": {"bookmark_count": 79, "bookmarked": false, "created_at": "Mon May 13 17:17:53 +0000 2024", "conversation_id_str": "1790068965126852770", "display_text_range": [0, 117], "entities": {"hashtags": [], "media": [{"display_url": "pic.x.com/uudy4hgjmu", "expanded_url": "https://twitter.com/norimyxxxo/status/1790068965126852770/video/1", "id_str": "1790068861733081088", "indices": [118, 141], "media_key": "13_1790068861733081088", "media_url_https": "https://pbs.twimg.com/amplify_video_thumb/1790068861733081088/img/hxqXQpygxuAmR6UT.jpg", "type": "video", "url": "https://t.co/uUdY4HgJmU", "additional_media_info": {"monetizable": false}, "ext_media_availability": {"status": "Available"}, "sizes": {"large": {"h": 1080, "w": 1080, "resize": "fit"}, "medium": {"h": 1080, "w": 1080, "resize": "fit"}, "small": {"h": 680, "w": 680, "resize": "fit"}, "thumb": {"h": 150, "w": 150, "resize": "crop"}}, "original_info": {"height": 1080, "width": 1080, "focus_rects": []}, "video_info": {"aspect_ratio": [1, 1], "duration_millis": 16041, "variants": [{"content_type": "application/x-mpegURL", "url": "https://video.twimg.com/amplify_video/1790068861733081088/pl/rqf8kyQZxOBYmRDZ.m3u8?tag=14&container=cmaf"}, {"bitrate": 432000, "content_type": "video/mp4", "url": "https://video.twimg.com/amplify_video/1790068861733081088/vid/avc1/320x320/OnSeSmtfceljxpwR.mp4?tag=14"}, {"bitrate": 832000, "content_type": "video/mp4", "url": "https://video.twimg.com/amplify_video/1790068861733081088/vid/avc1/540x540/WHrr-lyOPWiap4iz.mp4?tag=14"}, {"bitrate": 1280000, "content_type": "video/mp4", "url": "https://video.twimg.com/amplify_video/1790068861733081088/vid/avc1/720x720/hOmaJAM_as-8IAyN.mp4?tag=14"}]}, "media_results": {"result": {"media_key": "13_1790068861733081088"}}}], "symbols": [], "timestamps": [], "urls": [{"display_url": "band.link/mirgorit", "expanded_url": "https://band.link/mirgorit", "url": "https://t.co/U3a6MP9nVo", "indices": [32, 55]}], "user_mentions": [{"id_str": "28249315", "name": "PORCHY\ud83e\ude9d", "screen_name": "kingporchy", "indices": [73, 84]}]}, "extended_entities": {"media": [{"display_url": "pic.twitter.com/uUdY4HgJmU", "expanded_url": "https://twitter.com/norimyxxxo/status/1790068965126852770/video/1", "id_str": "1790068861733081088", "indices": [118, 141], "media_key": "13_1790068861733081088", "media_url_https": "https://pbs.twimg.com/amplify_video_thumb/1790068861733081088/img/hxqXQpygxuAmR6UT.jpg", "type": "video", "url": "https://t.co/uUdY4HgJmU", "additional_media_info": {"monetizable": false}, "ext_media_availability": {"status": "Available"}, "sizes": {"large": {"h": 1080, "w": 1080, "resize": "fit"}, "medium": {"h": 1080, "w": 1080, "resize": "fit"}, "small": {"h": 680, "w": 680, "resize": "fit"}, "thumb": {"h": 150, "w": 150, "resize": "crop"}}, "original_info": {"height": 1080, "width": 1080, "focus_rects": []}, "video_info": {"aspect_ratio": [1, 1], "duration_millis": 16041, "variants": [{"content_type": "application/x-mpegURL", "url": "https://video.twimg.com/amplify_video/1790068861733081088/pl/rqf8kyQZxOBYmRDZ.m3u8?tag=14&container=cmaf"}, {"bitrate": 432000, "content_type": "video/mp4", "url": "https://video.twimg.com/amplify_video/1790068861733081088/vid/avc1/320x320/OnSeSmtfceljxpwR.mp4?tag=14"}, {"bitrate": 832000, "content_type": "video/mp4", "url": "https://video.twimg.com/amplify_video/1790068861733081088/vid/avc1/540x540/WHrr-lyOPWiap4iz.mp4?tag=14"}, {"bitrate": 1280000, "content_type": "video/mp4", "url": "https://video.twimg.com/amplify_video/1790068861733081088/vid/avc1/720x720/hOmaJAM_as-8IAyN.mp4?tag=14"}]}, "media_results": {"result": {"media_key": "13_1790068861733081088"}}}]}, "favorite_count": 2830, "favorited": false, "full_text": "OXXXYMIRON \u2014 \u041c\u0418\u0420 \u0413\u041e\u0420\u0418\u0422 (2024):\n\nhttps://t.co/U3a6MP9nVo\n\nprod. by PORCHY @kingporchy\n\nEP \u00ab\u041d\u0410\u0426\u0418\u041e\u041d\u0410\u041b\u042c\u041d\u041e\u0421\u0422\u042c: \u041d\u0415\u0422\u00bb\n\n\u0421\u041a\u041e\u0420\u041e https://t.co/uUdY4HgJmU", "is_quote_status": false, "lang": "und", "possibly_sensitive": false, "possibly_sensitive_editable": true, "quote_count": 153, "reply_count": 106, "retweet_count": 243, "retweeted": false, "user_id_str": "111425302", "id_str": "1790068965126852770"}, "quick_promote_eligibility": {"eligibility": "IneligibleNotProfessional"}}}, "tweetDisplayType": "Tweet", "socialContext": {"type": "TimelineGeneralContext", "contextType": "Pin", "text": "Pinned"}}, "clientEventInfo": {"component": "pinned_tweets", "element": "tweet"}}}}, {"type": "TimelineAddEntries", "entries": [{"entryId": "cursor-top-1779110906735623272", "sortIndex": "1779110906735623272", "content": {"entryType": "TimelineTimelineCursor", "__typename": "TimelineTimelineCursor", "value": "DAABCgABGLCr8YwAI3gKAAIN_m9i-BfgAAgAAwAAAAEAAA", "cursorType": "Top"}}, {"entryId": "cursor-bottom-1779110906735623270", "sortIndex": "1779110906735623270", "content": {"entryType": "TimelineTimelineCursor", "__typename": "TimelineTimelineCursor", "value": "DAABCgABGLCr8Yv__GQKAAIN_m9i-BfgAAgAAwAAAAIAAA", "cursorType": "Bottom"}}]}], "metadata": {"scribeConfig": {"page": "profileBest"}}}}}}}}